Metadata-Version: 1.2
Name: ccs-compendium
Version: 0.0.6
Summary: CCS Compendium - creating a compendium for reproducible science
Home-page: http://github.com/ccs-amsterdam/ccs-compendium
Author: Wouter van Atteveldt
Author-email: wouter@vanatteveldt.com
License: MIT
Platform: UNKNOWN
Classifier: License :: OSI Approved :: MIT License
Classifier: Operating System :: OS Independent
Classifier: Programming Language :: Python :: 3
Classifier: Programming Language :: Python :: 3.5
Classifier: Programming Language :: Python :: 3.6
Classifier: Programming Language :: Python :: 3.7
Classifier: Programming Language :: Python :: 3.8
Classifier: Intended Audience :: Developers
Classifier: Intended Audience :: Science/Research
Classifier: Topic :: Scientific/Engineering
Requires-Python: >=3.6
